MANIFEST.in
README.md
setup.py
django_admin_visualsearch.egg-info/PKG-INFO
django_admin_visualsearch.egg-info/SOURCES.txt
django_admin_visualsearch.egg-info/dependency_links.txt
django_admin_visualsearch.egg-info/not-zip-safe
django_admin_visualsearch.egg-info/top_level.txt
visualsearch/__init__.py
visualsearch/admin.py
visualsearch/urls.py
visualsearch/views.py
visualsearch/static/css/visualsearch-datauri.css
visualsearch/static/js/dependencies.js
visualsearch/static/js/visualsearch.js
visualsearch/templates/admin/visualsearch/change_list.html
visualsearch/templates/admin/visualsearch/visual_search.html
visualsearch/templatetags/__init__.py
visualsearch/templatetags/visual_search.py