Metadata-Version: 1.0
Name: django-admin-visualsearch
Version: 1.2
Summary: Visualsearch.js for Django admin
Home-page: https://github.com/unk2k/django-admin-visualsearch
Author: Constantin Slednev
Author-email: c.slednev@gmail.com
License: BSD
Platform: any
Classifier: Development Status :: 5 - Production/Stable
Classifier: Environment :: Web Environment
Classifier: Intended Audience :: Developers
Classifier: License :: OSI Approved :: BSD License
Classifier: Operating System :: OS Independent
Classifier: Programming Language :: Python
Classifier: Topic :: Internet :: WWW/HTTP :: Dynamic Content
Classifier: Topic :: Internet :: WWW/HTTP :: Indexing/Search
Classifier: Framework :: Django
